{
  "benchmark": "cartpole",
  "method": "dqn",
  "seed": 456,
  "timestamp": "2026-05-02T05:46:33Z",
  "environment": {
    "torch_version": "2.11.0+cu130",
    "python_version": "3.12.3",
    "platform": "Linux",
    "platform_release": "6.17.0-22-generic",
    "cuda_version": "13.0",
    "gpu_model": "NVIDIA GeForce RTX 5090",
    "gpu_count": 1,
    "peak_gpu_memory_mb": 0.0
  },
  "hyperparameters": {
    "total_timesteps": 1000000,
    "eval_episodes": 50,
    "net_arch": [
      16
    ],
    "param_count": 228
  },
  "metrics": {
    "final_accuracy": 0.18246861924686192,
    "best_accuracy": 0.18246861924686192,
    "wall_time_seconds": 207.98059821128845,
    "peak_gpu_memory_mb": 0.0,
    "function_evals": 1000000,
    "total_steps": 1000000,
    "final_return": 109.22,
    "best_return": 128.05,
    "normalized_score": 0.18246861924686192,
    "rl_env_steps": 1025000,
    "success_rate": 0.0,
    "episode_length": 109.22
  },
  "epoch_logs": [
    {
      "epoch": 0,
      "accuracy": 0.0,
      "loss": -12.1,
      "time": 0.0
    },
    {
      "epoch": 1,
      "accuracy": 0.0,
      "loss": -9.2,
      "time": 12500.0
    },
    {
      "epoch": 2,
      "accuracy": 0.0,
      "loss": -9.45,
      "time": 25000.0
    },
    {
      "epoch": 3,
      "accuracy": 0.0,
      "loss": -9.45,
      "time": 37500.0
    },
    {
      "epoch": 4,
      "accuracy": 0.0,
      "loss": -9.45,
      "time": 50000.0
    },
    {
      "epoch": 5,
      "accuracy": 0.0,
      "loss": -9.45,
      "time": 62500.0
    },
    {
      "epoch": 6,
      "accuracy": 0.0,
      "loss": -9.6,
      "time": 75000.0
    },
    {
      "epoch": 7,
      "accuracy": 0.0,
      "loss": -10.65,
      "time": 87500.0
    },
    {
      "epoch": 8,
      "accuracy": 0.0,
      "loss": -12.75,
      "time": 100000.0
    },
    {
      "epoch": 9,
      "accuracy": 0.0,
      "loss": -25.4,
      "time": 112500.0
    },
    {
      "epoch": 10,
      "accuracy": 0.0,
      "loss": -39.7,
      "time": 125000.0
    },
    {
      "epoch": 11,
      "accuracy": 0.0,
      "loss": -32.8,
      "time": 137500.0
    },
    {
      "epoch": 12,
      "accuracy": 0.0,
      "loss": -29.75,
      "time": 150000.0
    },
    {
      "epoch": 13,
      "accuracy": 0.0,
      "loss": -15.85,
      "time": 162500.0
    },
    {
      "epoch": 14,
      "accuracy": 0.0,
      "loss": -14.45,
      "time": 175000.0
    },
    {
      "epoch": 15,
      "accuracy": 0.0,
      "loss": -13.2,
      "time": 187500.0
    },
    {
      "epoch": 16,
      "accuracy": 0.0,
      "loss": -11.8,
      "time": 200000.0
    },
    {
      "epoch": 17,
      "accuracy": 0.0,
      "loss": -10.9,
      "time": 212500.0
    },
    {
      "epoch": 18,
      "accuracy": 0.0,
      "loss": -11.0,
      "time": 225000.0
    },
    {
      "epoch": 19,
      "accuracy": 0.0,
      "loss": -10.7,
      "time": 237500.0
    },
    {
      "epoch": 20,
      "accuracy": 0.0,
      "loss": -10.35,
      "time": 250000.0
    },
    {
      "epoch": 21,
      "accuracy": 0.0,
      "loss": -10.35,
      "time": 262500.0
    },
    {
      "epoch": 22,
      "accuracy": 0.0,
      "loss": -11.0,
      "time": 275000.0
    },
    {
      "epoch": 23,
      "accuracy": 0.0,
      "loss": -10.85,
      "time": 287500.0
    },
    {
      "epoch": 24,
      "accuracy": 0.0,
      "loss": -11.05,
      "time": 300000.0
    },
    {
      "epoch": 25,
      "accuracy": 0.0,
      "loss": -12.25,
      "time": 312500.0
    },
    {
      "epoch": 26,
      "accuracy": 0.0,
      "loss": -13.2,
      "time": 325000.0
    },
    {
      "epoch": 27,
      "accuracy": 0.0,
      "loss": -13.6,
      "time": 337500.0
    },
    {
      "epoch": 28,
      "accuracy": 0.0,
      "loss": -14.9,
      "time": 350000.0
    },
    {
      "epoch": 29,
      "accuracy": 0.0,
      "loss": -16.4,
      "time": 362500.0
    },
    {
      "epoch": 30,
      "accuracy": 0.0,
      "loss": -18.2,
      "time": 375000.0
    },
    {
      "epoch": 31,
      "accuracy": 0.0,
      "loss": -23.9,
      "time": 387500.0
    },
    {
      "epoch": 32,
      "accuracy": 0.0,
      "loss": -41.05,
      "time": 400000.0
    },
    {
      "epoch": 33,
      "accuracy": 0.0,
      "loss": -86.95,
      "time": 412500.0
    },
    {
      "epoch": 34,
      "accuracy": 0.0,
      "loss": -102.6,
      "time": 425000.0
    },
    {
      "epoch": 35,
      "accuracy": 0.0,
      "loss": -118.8,
      "time": 437500.0
    },
    {
      "epoch": 36,
      "accuracy": 0.0,
      "loss": -105.8,
      "time": 450000.0
    },
    {
      "epoch": 37,
      "accuracy": 0.0,
      "loss": -79.05,
      "time": 462500.0
    },
    {
      "epoch": 38,
      "accuracy": 0.0,
      "loss": -76.75,
      "time": 475000.0
    },
    {
      "epoch": 39,
      "accuracy": 0.0,
      "loss": -61.65,
      "time": 487500.0
    },
    {
      "epoch": 40,
      "accuracy": 0.0,
      "loss": -55.95,
      "time": 500000.0
    },
    {
      "epoch": 41,
      "accuracy": 0.0,
      "loss": -50.85,
      "time": 512500.0
    },
    {
      "epoch": 42,
      "accuracy": 0.0,
      "loss": -44.05,
      "time": 525000.0
    },
    {
      "epoch": 43,
      "accuracy": 0.0,
      "loss": -45.6,
      "time": 537500.0
    },
    {
      "epoch": 44,
      "accuracy": 0.0,
      "loss": -49.1,
      "time": 550000.0
    },
    {
      "epoch": 45,
      "accuracy": 0.0,
      "loss": -44.65,
      "time": 562500.0
    },
    {
      "epoch": 46,
      "accuracy": 0.0,
      "loss": -42.1,
      "time": 575000.0
    },
    {
      "epoch": 47,
      "accuracy": 0.0,
      "loss": -43.7,
      "time": 587500.0
    },
    {
      "epoch": 48,
      "accuracy": 0.0,
      "loss": -52.7,
      "time": 600000.0
    },
    {
      "epoch": 49,
      "accuracy": 0.0,
      "loss": -53.85,
      "time": 612500.0
    },
    {
      "epoch": 50,
      "accuracy": 0.0,
      "loss": -54.65,
      "time": 625000.0
    },
    {
      "epoch": 51,
      "accuracy": 0.0,
      "loss": -60.4,
      "time": 637500.0
    },
    {
      "epoch": 52,
      "accuracy": 0.0,
      "loss": -63.55,
      "time": 650000.0
    },
    {
      "epoch": 53,
      "accuracy": 0.0,
      "loss": -66.35,
      "time": 662500.0
    },
    {
      "epoch": 54,
      "accuracy": 0.0,
      "loss": -68.85,
      "time": 675000.0
    },
    {
      "epoch": 55,
      "accuracy": 0.0,
      "loss": -77.0,
      "time": 687500.0
    },
    {
      "epoch": 56,
      "accuracy": 0.0,
      "loss": -100.15,
      "time": 700000.0
    },
    {
      "epoch": 57,
      "accuracy": 0.0,
      "loss": -128.05,
      "time": 712500.0
    },
    {
      "epoch": 58,
      "accuracy": 0.0,
      "loss": -126.4,
      "time": 725000.0
    },
    {
      "epoch": 59,
      "accuracy": 0.0,
      "loss": -124.7,
      "time": 737500.0
    },
    {
      "epoch": 60,
      "accuracy": 0.0,
      "loss": -125.6,
      "time": 750000.0
    },
    {
      "epoch": 61,
      "accuracy": 0.0,
      "loss": -116.25,
      "time": 762500.0
    },
    {
      "epoch": 62,
      "accuracy": 0.0,
      "loss": -99.0,
      "time": 775000.0
    },
    {
      "epoch": 63,
      "accuracy": 0.0,
      "loss": -85.6,
      "time": 787500.0
    },
    {
      "epoch": 64,
      "accuracy": 0.0,
      "loss": -81.65,
      "time": 800000.0
    },
    {
      "epoch": 65,
      "accuracy": 0.0,
      "loss": -76.25,
      "time": 812500.0
    },
    {
      "epoch": 66,
      "accuracy": 0.0,
      "loss": -72.65,
      "time": 825000.0
    },
    {
      "epoch": 67,
      "accuracy": 0.0,
      "loss": -75.45,
      "time": 837500.0
    },
    {
      "epoch": 68,
      "accuracy": 0.0,
      "loss": -75.7,
      "time": 850000.0
    },
    {
      "epoch": 69,
      "accuracy": 0.0,
      "loss": -77.85,
      "time": 862500.0
    },
    {
      "epoch": 70,
      "accuracy": 0.0,
      "loss": -78.3,
      "time": 875000.0
    },
    {
      "epoch": 71,
      "accuracy": 0.0,
      "loss": -81.0,
      "time": 887500.0
    },
    {
      "epoch": 72,
      "accuracy": 0.0,
      "loss": -83.3,
      "time": 900000.0
    },
    {
      "epoch": 73,
      "accuracy": 0.0,
      "loss": -83.9,
      "time": 912500.0
    },
    {
      "epoch": 74,
      "accuracy": 0.0,
      "loss": -88.1,
      "time": 925000.0
    },
    {
      "epoch": 75,
      "accuracy": 0.0,
      "loss": -92.3,
      "time": 937500.0
    },
    {
      "epoch": 76,
      "accuracy": 0.0,
      "loss": -91.5,
      "time": 950000.0
    },
    {
      "epoch": 77,
      "accuracy": 0.0,
      "loss": -95.55,
      "time": 962500.0
    },
    {
      "epoch": 78,
      "accuracy": 0.0,
      "loss": -92.8,
      "time": 975000.0
    },
    {
      "epoch": 79,
      "accuracy": 0.0,
      "loss": -96.0,
      "time": 987500.0
    },
    {
      "epoch": 80,
      "accuracy": 0.0,
      "loss": -100.2,
      "time": 1000000.0
    }
  ],
  "step_logs": [
    {
      "step": 0,
      "epoch": 0,
      "env_steps_cumulative": 0,
      "mean_return": 12.1,
      "episode_length": 12.1,
      "loss": -12.1,
      "time": 0.0
    },
    {
      "step": 1,
      "epoch": 1,
      "env_steps_cumulative": 12500,
      "mean_return": 9.2,
      "episode_length": 9.2,
      "loss": -9.2,
      "time": 12500.0
    },
    {
      "step": 2,
      "epoch": 2,
      "env_steps_cumulative": 25000,
      "mean_return": 9.45,
      "episode_length": 9.45,
      "loss": -9.45,
      "time": 25000.0
    },
    {
      "step": 3,
      "epoch": 3,
      "env_steps_cumulative": 37500,
      "mean_return": 9.45,
      "episode_length": 9.45,
      "loss": -9.45,
      "time": 37500.0
    },
    {
      "step": 4,
      "epoch": 4,
      "env_steps_cumulative": 50000,
      "mean_return": 9.45,
      "episode_length": 9.45,
      "loss": -9.45,
      "time": 50000.0
    },
    {
      "step": 5,
      "epoch": 5,
      "env_steps_cumulative": 62500,
      "mean_return": 9.45,
      "episode_length": 9.45,
      "loss": -9.45,
      "time": 62500.0
    },
    {
      "step": 6,
      "epoch": 6,
      "env_steps_cumulative": 75000,
      "mean_return": 9.6,
      "episode_length": 9.6,
      "loss": -9.6,
      "time": 75000.0
    },
    {
      "step": 7,
      "epoch": 7,
      "env_steps_cumulative": 87500,
      "mean_return": 10.65,
      "episode_length": 10.65,
      "loss": -10.65,
      "time": 87500.0
    },
    {
      "step": 8,
      "epoch": 8,
      "env_steps_cumulative": 100000,
      "mean_return": 12.75,
      "episode_length": 12.75,
      "loss": -12.75,
      "time": 100000.0
    },
    {
      "step": 9,
      "epoch": 9,
      "env_steps_cumulative": 112500,
      "mean_return": 25.4,
      "episode_length": 25.4,
      "loss": -25.4,
      "time": 112500.0
    },
    {
      "step": 10,
      "epoch": 10,
      "env_steps_cumulative": 125000,
      "mean_return": 39.7,
      "episode_length": 39.7,
      "loss": -39.7,
      "time": 125000.0
    },
    {
      "step": 11,
      "epoch": 11,
      "env_steps_cumulative": 137500,
      "mean_return": 32.8,
      "episode_length": 32.8,
      "loss": -32.8,
      "time": 137500.0
    },
    {
      "step": 12,
      "epoch": 12,
      "env_steps_cumulative": 150000,
      "mean_return": 29.75,
      "episode_length": 29.75,
      "loss": -29.75,
      "time": 150000.0
    },
    {
      "step": 13,
      "epoch": 13,
      "env_steps_cumulative": 162500,
      "mean_return": 15.85,
      "episode_length": 15.85,
      "loss": -15.85,
      "time": 162500.0
    },
    {
      "step": 14,
      "epoch": 14,
      "env_steps_cumulative": 175000,
      "mean_return": 14.45,
      "episode_length": 14.45,
      "loss": -14.45,
      "time": 175000.0
    },
    {
      "step": 15,
      "epoch": 15,
      "env_steps_cumulative": 187500,
      "mean_return": 13.2,
      "episode_length": 13.2,
      "loss": -13.2,
      "time": 187500.0
    },
    {
      "step": 16,
      "epoch": 16,
      "env_steps_cumulative": 200000,
      "mean_return": 11.8,
      "episode_length": 11.8,
      "loss": -11.8,
      "time": 200000.0
    },
    {
      "step": 17,
      "epoch": 17,
      "env_steps_cumulative": 212500,
      "mean_return": 10.9,
      "episode_length": 10.9,
      "loss": -10.9,
      "time": 212500.0
    },
    {
      "step": 18,
      "epoch": 18,
      "env_steps_cumulative": 225000,
      "mean_return": 11.0,
      "episode_length": 11.0,
      "loss": -11.0,
      "time": 225000.0
    },
    {
      "step": 19,
      "epoch": 19,
      "env_steps_cumulative": 237500,
      "mean_return": 10.7,
      "episode_length": 10.7,
      "loss": -10.7,
      "time": 237500.0
    },
    {
      "step": 20,
      "epoch": 20,
      "env_steps_cumulative": 250000,
      "mean_return": 10.35,
      "episode_length": 10.35,
      "loss": -10.35,
      "time": 250000.0
    },
    {
      "step": 21,
      "epoch": 21,
      "env_steps_cumulative": 262500,
      "mean_return": 10.35,
      "episode_length": 10.35,
      "loss": -10.35,
      "time": 262500.0
    },
    {
      "step": 22,
      "epoch": 22,
      "env_steps_cumulative": 275000,
      "mean_return": 11.0,
      "episode_length": 11.0,
      "loss": -11.0,
      "time": 275000.0
    },
    {
      "step": 23,
      "epoch": 23,
      "env_steps_cumulative": 287500,
      "mean_return": 10.85,
      "episode_length": 10.85,
      "loss": -10.85,
      "time": 287500.0
    },
    {
      "step": 24,
      "epoch": 24,
      "env_steps_cumulative": 300000,
      "mean_return": 11.05,
      "episode_length": 11.05,
      "loss": -11.05,
      "time": 300000.0
    },
    {
      "step": 25,
      "epoch": 25,
      "env_steps_cumulative": 312500,
      "mean_return": 12.25,
      "episode_length": 12.25,
      "loss": -12.25,
      "time": 312500.0
    },
    {
      "step": 26,
      "epoch": 26,
      "env_steps_cumulative": 325000,
      "mean_return": 13.2,
      "episode_length": 13.2,
      "loss": -13.2,
      "time": 325000.0
    },
    {
      "step": 27,
      "epoch": 27,
      "env_steps_cumulative": 337500,
      "mean_return": 13.6,
      "episode_length": 13.6,
      "loss": -13.6,
      "time": 337500.0
    },
    {
      "step": 28,
      "epoch": 28,
      "env_steps_cumulative": 350000,
      "mean_return": 14.9,
      "episode_length": 14.9,
      "loss": -14.9,
      "time": 350000.0
    },
    {
      "step": 29,
      "epoch": 29,
      "env_steps_cumulative": 362500,
      "mean_return": 16.4,
      "episode_length": 16.4,
      "loss": -16.4,
      "time": 362500.0
    },
    {
      "step": 30,
      "epoch": 30,
      "env_steps_cumulative": 375000,
      "mean_return": 18.2,
      "episode_length": 18.2,
      "loss": -18.2,
      "time": 375000.0
    },
    {
      "step": 31,
      "epoch": 31,
      "env_steps_cumulative": 387500,
      "mean_return": 23.9,
      "episode_length": 23.9,
      "loss": -23.9,
      "time": 387500.0
    },
    {
      "step": 32,
      "epoch": 32,
      "env_steps_cumulative": 400000,
      "mean_return": 41.05,
      "episode_length": 41.05,
      "loss": -41.05,
      "time": 400000.0
    },
    {
      "step": 33,
      "epoch": 33,
      "env_steps_cumulative": 412500,
      "mean_return": 86.95,
      "episode_length": 86.95,
      "loss": -86.95,
      "time": 412500.0
    },
    {
      "step": 34,
      "epoch": 34,
      "env_steps_cumulative": 425000,
      "mean_return": 102.6,
      "episode_length": 102.6,
      "loss": -102.6,
      "time": 425000.0
    },
    {
      "step": 35,
      "epoch": 35,
      "env_steps_cumulative": 437500,
      "mean_return": 118.8,
      "episode_length": 118.8,
      "loss": -118.8,
      "time": 437500.0
    },
    {
      "step": 36,
      "epoch": 36,
      "env_steps_cumulative": 450000,
      "mean_return": 105.8,
      "episode_length": 105.8,
      "loss": -105.8,
      "time": 450000.0
    },
    {
      "step": 37,
      "epoch": 37,
      "env_steps_cumulative": 462500,
      "mean_return": 79.05,
      "episode_length": 79.05,
      "loss": -79.05,
      "time": 462500.0
    },
    {
      "step": 38,
      "epoch": 38,
      "env_steps_cumulative": 475000,
      "mean_return": 76.75,
      "episode_length": 76.75,
      "loss": -76.75,
      "time": 475000.0
    },
    {
      "step": 39,
      "epoch": 39,
      "env_steps_cumulative": 487500,
      "mean_return": 61.65,
      "episode_length": 61.65,
      "loss": -61.65,
      "time": 487500.0
    },
    {
      "step": 40,
      "epoch": 40,
      "env_steps_cumulative": 500000,
      "mean_return": 55.95,
      "episode_length": 55.95,
      "loss": -55.95,
      "time": 500000.0
    },
    {
      "step": 41,
      "epoch": 41,
      "env_steps_cumulative": 512500,
      "mean_return": 50.85,
      "episode_length": 50.85,
      "loss": -50.85,
      "time": 512500.0
    },
    {
      "step": 42,
      "epoch": 42,
      "env_steps_cumulative": 525000,
      "mean_return": 44.05,
      "episode_length": 44.05,
      "loss": -44.05,
      "time": 525000.0
    },
    {
      "step": 43,
      "epoch": 43,
      "env_steps_cumulative": 537500,
      "mean_return": 45.6,
      "episode_length": 45.6,
      "loss": -45.6,
      "time": 537500.0
    },
    {
      "step": 44,
      "epoch": 44,
      "env_steps_cumulative": 550000,
      "mean_return": 49.1,
      "episode_length": 49.1,
      "loss": -49.1,
      "time": 550000.0
    },
    {
      "step": 45,
      "epoch": 45,
      "env_steps_cumulative": 562500,
      "mean_return": 44.65,
      "episode_length": 44.65,
      "loss": -44.65,
      "time": 562500.0
    },
    {
      "step": 46,
      "epoch": 46,
      "env_steps_cumulative": 575000,
      "mean_return": 42.1,
      "episode_length": 42.1,
      "loss": -42.1,
      "time": 575000.0
    },
    {
      "step": 47,
      "epoch": 47,
      "env_steps_cumulative": 587500,
      "mean_return": 43.7,
      "episode_length": 43.7,
      "loss": -43.7,
      "time": 587500.0
    },
    {
      "step": 48,
      "epoch": 48,
      "env_steps_cumulative": 600000,
      "mean_return": 52.7,
      "episode_length": 52.7,
      "loss": -52.7,
      "time": 600000.0
    },
    {
      "step": 49,
      "epoch": 49,
      "env_steps_cumulative": 612500,
      "mean_return": 53.85,
      "episode_length": 53.85,
      "loss": -53.85,
      "time": 612500.0
    },
    {
      "step": 50,
      "epoch": 50,
      "env_steps_cumulative": 625000,
      "mean_return": 54.65,
      "episode_length": 54.65,
      "loss": -54.65,
      "time": 625000.0
    },
    {
      "step": 51,
      "epoch": 51,
      "env_steps_cumulative": 637500,
      "mean_return": 60.4,
      "episode_length": 60.4,
      "loss": -60.4,
      "time": 637500.0
    },
    {
      "step": 52,
      "epoch": 52,
      "env_steps_cumulative": 650000,
      "mean_return": 63.55,
      "episode_length": 63.55,
      "loss": -63.55,
      "time": 650000.0
    },
    {
      "step": 53,
      "epoch": 53,
      "env_steps_cumulative": 662500,
      "mean_return": 66.35,
      "episode_length": 66.35,
      "loss": -66.35,
      "time": 662500.0
    },
    {
      "step": 54,
      "epoch": 54,
      "env_steps_cumulative": 675000,
      "mean_return": 68.85,
      "episode_length": 68.85,
      "loss": -68.85,
      "time": 675000.0
    },
    {
      "step": 55,
      "epoch": 55,
      "env_steps_cumulative": 687500,
      "mean_return": 77.0,
      "episode_length": 77.0,
      "loss": -77.0,
      "time": 687500.0
    },
    {
      "step": 56,
      "epoch": 56,
      "env_steps_cumulative": 700000,
      "mean_return": 100.15,
      "episode_length": 100.15,
      "loss": -100.15,
      "time": 700000.0
    },
    {
      "step": 57,
      "epoch": 57,
      "env_steps_cumulative": 712500,
      "mean_return": 128.05,
      "episode_length": 128.05,
      "loss": -128.05,
      "time": 712500.0
    },
    {
      "step": 58,
      "epoch": 58,
      "env_steps_cumulative": 725000,
      "mean_return": 126.4,
      "episode_length": 126.4,
      "loss": -126.4,
      "time": 725000.0
    },
    {
      "step": 59,
      "epoch": 59,
      "env_steps_cumulative": 737500,
      "mean_return": 124.7,
      "episode_length": 124.7,
      "loss": -124.7,
      "time": 737500.0
    },
    {
      "step": 60,
      "epoch": 60,
      "env_steps_cumulative": 750000,
      "mean_return": 125.6,
      "episode_length": 125.6,
      "loss": -125.6,
      "time": 750000.0
    },
    {
      "step": 61,
      "epoch": 61,
      "env_steps_cumulative": 762500,
      "mean_return": 116.25,
      "episode_length": 116.25,
      "loss": -116.25,
      "time": 762500.0
    },
    {
      "step": 62,
      "epoch": 62,
      "env_steps_cumulative": 775000,
      "mean_return": 99.0,
      "episode_length": 99.0,
      "loss": -99.0,
      "time": 775000.0
    },
    {
      "step": 63,
      "epoch": 63,
      "env_steps_cumulative": 787500,
      "mean_return": 85.6,
      "episode_length": 85.6,
      "loss": -85.6,
      "time": 787500.0
    },
    {
      "step": 64,
      "epoch": 64,
      "env_steps_cumulative": 800000,
      "mean_return": 81.65,
      "episode_length": 81.65,
      "loss": -81.65,
      "time": 800000.0
    },
    {
      "step": 65,
      "epoch": 65,
      "env_steps_cumulative": 812500,
      "mean_return": 76.25,
      "episode_length": 76.25,
      "loss": -76.25,
      "time": 812500.0
    },
    {
      "step": 66,
      "epoch": 66,
      "env_steps_cumulative": 825000,
      "mean_return": 72.65,
      "episode_length": 72.65,
      "loss": -72.65,
      "time": 825000.0
    },
    {
      "step": 67,
      "epoch": 67,
      "env_steps_cumulative": 837500,
      "mean_return": 75.45,
      "episode_length": 75.45,
      "loss": -75.45,
      "time": 837500.0
    },
    {
      "step": 68,
      "epoch": 68,
      "env_steps_cumulative": 850000,
      "mean_return": 75.7,
      "episode_length": 75.7,
      "loss": -75.7,
      "time": 850000.0
    },
    {
      "step": 69,
      "epoch": 69,
      "env_steps_cumulative": 862500,
      "mean_return": 77.85,
      "episode_length": 77.85,
      "loss": -77.85,
      "time": 862500.0
    },
    {
      "step": 70,
      "epoch": 70,
      "env_steps_cumulative": 875000,
      "mean_return": 78.3,
      "episode_length": 78.3,
      "loss": -78.3,
      "time": 875000.0
    },
    {
      "step": 71,
      "epoch": 71,
      "env_steps_cumulative": 887500,
      "mean_return": 81.0,
      "episode_length": 81.0,
      "loss": -81.0,
      "time": 887500.0
    },
    {
      "step": 72,
      "epoch": 72,
      "env_steps_cumulative": 900000,
      "mean_return": 83.3,
      "episode_length": 83.3,
      "loss": -83.3,
      "time": 900000.0
    },
    {
      "step": 73,
      "epoch": 73,
      "env_steps_cumulative": 912500,
      "mean_return": 83.9,
      "episode_length": 83.9,
      "loss": -83.9,
      "time": 912500.0
    },
    {
      "step": 74,
      "epoch": 74,
      "env_steps_cumulative": 925000,
      "mean_return": 88.1,
      "episode_length": 88.1,
      "loss": -88.1,
      "time": 925000.0
    },
    {
      "step": 75,
      "epoch": 75,
      "env_steps_cumulative": 937500,
      "mean_return": 92.3,
      "episode_length": 92.3,
      "loss": -92.3,
      "time": 937500.0
    },
    {
      "step": 76,
      "epoch": 76,
      "env_steps_cumulative": 950000,
      "mean_return": 91.5,
      "episode_length": 91.5,
      "loss": -91.5,
      "time": 950000.0
    },
    {
      "step": 77,
      "epoch": 77,
      "env_steps_cumulative": 962500,
      "mean_return": 95.55,
      "episode_length": 95.55,
      "loss": -95.55,
      "time": 962500.0
    },
    {
      "step": 78,
      "epoch": 78,
      "env_steps_cumulative": 975000,
      "mean_return": 92.8,
      "episode_length": 92.8,
      "loss": -92.8,
      "time": 975000.0
    },
    {
      "step": 79,
      "epoch": 79,
      "env_steps_cumulative": 987500,
      "mean_return": 96.0,
      "episode_length": 96.0,
      "loss": -96.0,
      "time": 987500.0
    },
    {
      "step": 80,
      "epoch": 80,
      "env_steps_cumulative": 1000000,
      "mean_return": 100.2,
      "episode_length": 100.2,
      "loss": -100.2,
      "time": 1000000.0
    }
  ]
}