{
  "benchmark": "taxi",
  "method": "polystep_sweep_1",
  "seed": 42,
  "timestamp": "2026-05-01T04:40:15Z",
  "environment": {
    "torch_version": "2.11.0+cu130",
    "python_version": "3.12.3",
    "platform": "Linux",
    "platform_release": "6.17.0-22-generic",
    "cuda_version": "13.0",
    "gpu_model": "NVIDIA GeForce RTX 5090",
    "gpu_count": 1,
    "peak_gpu_memory_mb": 0.0
  },
  "hyperparameters": {
    "representation": "tabular_q_table",
    "steps": 200,
    "rollouts_per_candidate": 128,
    "horizon": 200,
    "subspace_rank": 2,
    "epsilon_init": 1.0,
    "epsilon_target": 0.3,
    "step_radius": 0.1,
    "probe_radius": 0.2,
    "amortize_steps": 1,
    "max_subspace_dim": 16,
    "param_count": 3000,
    "subspace_dim": 16
  },
  "metrics": {
    "final_accuracy": 0.0,
    "best_accuracy": 0.0,
    "wall_time_seconds": 98.46082496643066,
    "peak_gpu_memory_mb": 0.0,
    "function_evals": 6400,
    "total_steps": 200,
    "final_return": -873.1015625,
    "best_return": -705.3359375,
    "normalized_score": 0.0,
    "rl_env_steps": 163840000,
    "success_rate": 0.0,
    "episode_length": 200.0,
    "illegal_action_rate": 0.37394529581069946,
    "best_success_rate": 0.0
  },
  "epoch_logs": [
    {
      "epoch": 1,
      "accuracy": 0.0,
      "loss": 971.8203125,
      "time": 0.13532304763793945
    },
    {
      "epoch": 20,
      "accuracy": 0.0,
      "loss": 1013.234375,
      "time": 4.151162147521973
    },
    {
      "epoch": 40,
      "accuracy": 0.0,
      "loss": 914.9375,
      "time": 15.979571104049683
    },
    {
      "epoch": 60,
      "accuracy": 0.0,
      "loss": 1083.7578125,
      "time": 19.19087314605713
    },
    {
      "epoch": 80,
      "accuracy": 0.0,
      "loss": 971.3984375,
      "time": 25.093777179718018
    },
    {
      "epoch": 100,
      "accuracy": 0.0,
      "loss": 844.90625,
      "time": 46.237475633621216
    },
    {
      "epoch": 120,
      "accuracy": 0.0,
      "loss": 705.3359375,
      "time": 60.697136878967285
    },
    {
      "epoch": 140,
      "accuracy": 0.0,
      "loss": 845.1875,
      "time": 72.69507265090942
    },
    {
      "epoch": 160,
      "accuracy": 0.0,
      "loss": 928.7890625,
      "time": 76.34487533569336
    },
    {
      "epoch": 180,
      "accuracy": 0.0,
      "loss": 845.5390625,
      "time": 87.32618880271912
    },
    {
      "epoch": 200,
      "accuracy": 0.0,
      "loss": 929.0,
      "time": 98.42393112182617
    }
  ],
  "step_logs": [
    {
      "step": 1,
      "epoch": 1,
      "accuracy": 0.0,
      "mean_return": -971.8203125,
      "success_rate": 0.0,
      "episode_length": 200.0,
      "illegal_action_rate": 0.42878901958465576,
      "loss": 971.8203125,
      "time": 0.13532304763793945,
      "step_wall_time": 0.09858036041259766,
      "candidates_evaluated": 32
    },
    {
      "step": 20,
      "epoch": 20,
      "accuracy": 0.0,
      "mean_return": -1013.234375,
      "success_rate": 0.0,
      "episode_length": 200.0,
      "illegal_action_rate": 0.45179688930511475,
      "loss": 1013.234375,
      "time": 4.151162147521973,
      "step_wall_time": 0.1630868911743164,
      "candidates_evaluated": 640
    },
    {
      "step": 40,
      "epoch": 40,
      "accuracy": 0.0,
      "mean_return": -914.9375,
      "success_rate": 0.0,
      "episode_length": 200.0,
      "illegal_action_rate": 0.3971874713897705,
      "loss": 914.9375,
      "time": 15.979571104049683,
      "step_wall_time": 0.10025906562805176,
      "candidates_evaluated": 1280
    },
    {
      "step": 60,
      "epoch": 60,
      "accuracy": 0.0,
      "mean_return": -1083.7578125,
      "success_rate": 0.0,
      "episode_length": 200.0,
      "illegal_action_rate": 0.4909765422344208,
      "loss": 1083.7578125,
      "time": 19.19087314605713,
      "step_wall_time": 0.12491250038146973,
      "candidates_evaluated": 1920
    },
    {
      "step": 80,
      "epoch": 80,
      "accuracy": 0.0,
      "mean_return": -971.3984375,
      "success_rate": 0.0,
      "episode_length": 200.0,
      "illegal_action_rate": 0.4285546541213989,
      "loss": 971.3984375,
      "time": 25.093777179718018,
      "step_wall_time": 0.1329648494720459,
      "candidates_evaluated": 2560
    },
    {
      "step": 100,
      "epoch": 100,
      "accuracy": 0.0,
      "mean_return": -844.90625,
      "success_rate": 0.0,
      "episode_length": 200.0,
      "illegal_action_rate": 0.3582812547683716,
      "loss": 844.90625,
      "time": 46.237475633621216,
      "step_wall_time": 0.8109924793243408,
      "candidates_evaluated": 3200
    },
    {
      "step": 120,
      "epoch": 120,
      "accuracy": 0.0,
      "mean_return": -705.3359375,
      "success_rate": 0.0,
      "episode_length": 200.0,
      "illegal_action_rate": 0.28074216842651367,
      "loss": 705.3359375,
      "time": 60.697136878967285,
      "step_wall_time": 0.10870885848999023,
      "candidates_evaluated": 3840
    },
    {
      "step": 140,
      "epoch": 140,
      "accuracy": 0.0,
      "mean_return": -845.1875,
      "success_rate": 0.0,
      "episode_length": 200.0,
      "illegal_action_rate": 0.3584374785423279,
      "loss": 845.1875,
      "time": 72.69507265090942,
      "step_wall_time": 0.12203550338745117,
      "candidates_evaluated": 4480
    },
    {
      "step": 160,
      "epoch": 160,
      "accuracy": 0.0,
      "mean_return": -928.7890625,
      "success_rate": 0.0,
      "episode_length": 200.0,
      "illegal_action_rate": 0.4048827886581421,
      "loss": 928.7890625,
      "time": 76.34487533569336,
      "step_wall_time": 0.11144614219665527,
      "candidates_evaluated": 5120
    },
    {
      "step": 180,
      "epoch": 180,
      "accuracy": 0.0,
      "mean_return": -845.5390625,
      "success_rate": 0.0,
      "episode_length": 200.0,
      "illegal_action_rate": 0.35863280296325684,
      "loss": 845.5390625,
      "time": 87.32618880271912,
      "step_wall_time": 0.9651858806610107,
      "candidates_evaluated": 5760
    },
    {
      "step": 200,
      "epoch": 200,
      "accuracy": 0.0,
      "mean_return": -929.0,
      "success_rate": 0.0,
      "episode_length": 200.0,
      "illegal_action_rate": 0.4050000011920929,
      "loss": 929.0,
      "time": 98.42393112182617,
      "step_wall_time": 0.13685393333435059,
      "candidates_evaluated": 6400
    }
  ]
}